auquan_qq14_toolbox/__init__.py
auquan_qq14_toolbox/problem2_data_loader.py
auquan_qq14_toolbox/problem2_execution_system.py
auquan_qq14_toolbox/problem2_time_rule.py
auquan_qq14_toolbox/problem2_trading_params.py
auquan_qq14_toolbox-0.0.6.dist-info/LICENSE
auquan_qq14_toolbox-0.0.6.dist-info/METADATA
auquan_qq14_toolbox-0.0.6.dist-info/WHEEL
auquan_qq14_toolbox-0.0.6.dist-info/top_level.txt
auquan_qq14_toolbox-0.0.6.dist-info/RECORD
