Metadata-Version: 2.1
Name: auquan-qq14-toolbox
Version: 0.0.6
Summary: Toolbox for QQ14
Home-page: UNKNOWN
Author: Auquan Team
Author-email: qqadmins@auquan.com
License: MIT
Keywords: auquan finance trading backtesting development
Platform: UNKNOWN
Classifier: Development Status :: 5 - Production/Stable
Classifier: Intended Audience :: Developers
Classifier: Topic :: Software Development :: Build Tools
Classifier: License :: OSI Approved :: MIT License
Classifier: Programming Language :: Python :: 3.6
Requires-Dist: requests
Requires-Dist: plotly
Requires-Dist: numpy
Requires-Dist: pandas
Requires-Dist: bs4
Requires-Dist: scipy
Requires-Dist: sklearn
Requires-Dist: lxml
Requires-Dist: auquan-toolbox
